Metadata-Version: 2.4
Name: mcp-server-jisuanqi
Version: 0.1.2
Summary: 一个基于MCP的简单计算器服务
Project-URL: Homepage, https://github.com/yourusername/mcp-server-jisuanqi
Project-URL: Repository, https://github.com/yourusername/mcp-server-jisuanqi.git
Author-email: Your Name <your.email@example.com>
License: MIT
Keywords: calculator,math,mcp
Requires-Python: >=3.10
Requires-Dist: mcp[cli]>=1.6.0
